[
  {
    "symbol": "GRRR",
    "prev_close": 11.65,
    "pm_price": 16.65,
    "gap_pct": 42.92,
    "pm_volume": 22641.0,
    "first_seen_et": "04:00",
    "sim_start": "07:00",
    "float_shares": null,
    "float_millions": null,
    "profile": "X"
  },
  {
    "symbol": "VMAR",
    "prev_close": 2.15,
    "pm_price": 2.81,
    "gap_pct": 30.7,
    "pm_volume": 21749861.0,
    "first_seen_et": "04:00",
    "sim_start": "07:00",
    "float_shares": 868696,
    "float_millions": 0.87,
    "profile": "A"
  },
  {
    "symbol": "AMOD",
    "prev_close": 1.92,
    "pm_price": 2.5,
    "gap_pct": 30.21,
    "pm_volume": 1537.0,
    "first_seen_et": "04:10",
    "sim_start": "07:00",
    "float_shares": null,
    "float_millions": null,
    "profile": "X"
  },
  {
    "symbol": "EZRA",
    "prev_close": 1.93,
    "pm_price": 2.47,
    "gap_pct": 27.98,
    "pm_volume": 109.0,
    "first_seen_et": "04:28",
    "sim_start": "07:00",
    "float_shares": null,
    "float_millions": null,
    "profile": "X"
  },
  {
    "symbol": "NVNI",
    "prev_close": 1.64,
    "pm_price": 2.05,
    "gap_pct": 25.0,
    "pm_volume": 6549.0,
    "first_seen_et": "05:00",
    "sim_start": "07:00",
    "float_shares": 7028202,
    "float_millions": 7.03,
    "profile": "B"
  },
  {
    "symbol": "MI",
    "prev_close": 2.6,
    "pm_price": 3.2,
    "gap_pct": 23.08,
    "pm_volume": 1606.0,
    "first_seen_et": "04:26",
    "sim_start": "07:00",
    "float_shares": 5065150,
    "float_millions": 5.07,
    "profile": "B"
  },
  {
    "symbol": "NCPL",
    "prev_close": 1.82,
    "pm_price": 2.06,
    "gap_pct": 13.19,
    "pm_volume": 3240.0,
    "first_seen_et": "04:06",
    "sim_start": "07:00",
    "float_shares": 3814431,
    "float_millions": 3.81,
    "profile": "A"
  },
  {
    "symbol": "XXII",
    "prev_close": 4.89,
    "pm_price": 5.51,
    "gap_pct": 12.68,
    "pm_volume": 7181.0,
    "first_seen_et": "04:01",
    "sim_start": "07:00",
    "float_shares": 419359,
    "float_millions": 0.42,
    "profile": "A"
  },
  {
    "symbol": "MAXN",
    "prev_close": 6.45,
    "pm_price": 7.24,
    "gap_pct": 12.25,
    "pm_volume": 924.0,
    "first_seen_et": "05:02",
    "sim_start": "07:00",
    "float_shares": 6808832,
    "float_millions": 6.81,
    "profile": "B"
  },
  {
    "symbol": "EHGO",
    "prev_close": 3.27,
    "pm_price": 3.65,
    "gap_pct": 11.62,
    "pm_volume": 16300.0,
    "first_seen_et": "04:15",
    "sim_start": "07:00",
    "float_shares": null,
    "float_millions": null,
    "profile": "X"
  },
  {
    "symbol": "DRN",
    "prev_close": 8.72,
    "pm_price": 9.71,
    "gap_pct": 11.35,
    "pm_volume": 533.0,
    "first_seen_et": "04:09",
    "sim_start": "07:00",
    "float_shares": null,
    "float_millions": null,
    "profile": "X"
  },
  {
    "symbol": "MSOX",
    "prev_close": 7.69,
    "pm_price": 8.55,
    "gap_pct": 11.18,
    "pm_volume": 100.0,
    "first_seen_et": "07:00",
    "sim_start": "07:00",
    "float_shares": null,
    "float_millions": null,
    "profile": "X"
  },
  {
    "symbol": "ASMB",
    "prev_close": 15.62,
    "pm_price": 17.29,
    "gap_pct": 10.69,
    "pm_volume": 709.0,
    "first_seen_et": "04:41",
    "sim_start": "07:00",
    "float_shares": 7458256,
    "float_millions": 7.46,
    "profile": "B"
  },
  {
    "symbol": "WHLR",
    "prev_close": 2.54,
    "pm_price": 2.8,
    "gap_pct": 10.24,
    "pm_volume": 12740.0,
    "first_seen_et": "04:08",
    "sim_start": "07:00",
    "float_shares": 186888,
    "float_millions": 0.19,
    "profile": "A"
  }
]