[
  {
    "symbol": "AXIL",
    "prev_close": 5.02,
    "pm_price": 10.97,
    "gap_pct": 118.53,
    "pm_volume": 7167189.0,
    "first_seen_et": "05:10",
    "sim_start": "05:12",
    "discovery_time": "05:12",
    "discovery_method": "precise",
    "avg_daily_volume": 9216.0,
    "relative_volume": 777.69,
    "precise_discovery": "05:12",
    "float_shares": 3463603,
    "float_millions": 3.46,
    "profile": "A"
  },
  {
    "symbol": "GLXG",
    "prev_close": 3.17,
    "pm_price": 3.76,
    "gap_pct": 18.61,
    "pm_volume": 2975561.0,
    "first_seen_et": "04:00",
    "sim_start": "04:07",
    "discovery_time": "04:07",
    "discovery_method": "precise",
    "avg_daily_volume": 49998.0,
    "relative_volume": 59.51,
    "precise_discovery": "04:07",
    "float_shares": 545523,
    "float_millions": 0.55,
    "profile": "A"
  },
  {
    "symbol": "BTTC",
    "prev_close": 3.315,
    "pm_price": 4.89,
    "gap_pct": 47.51,
    "pm_volume": 124982.0,
    "first_seen_et": "08:30",
    "sim_start": "08:30",
    "discovery_time": "08:30",
    "discovery_method": "rescan",
    "avg_daily_volume": 28316.0,
    "relative_volume": 4.41,
    "precise_discovery": "08:30",
    "float_shares": 1271887,
    "float_millions": 1.27,
    "profile": "A"
  }
]