[
  {
    "symbol": "POLA",
    "prev_close": 2.84,
    "pm_price": 3.45,
    "gap_pct": 21.48,
    "pm_volume": 349764.0,
    "first_seen_et": "04:00",
    "sim_start": "04:00",
    "discovery_time": "04:00",
    "discovery_method": "ibkr_historical",
    "avg_daily_volume": 25960.0,
    "relative_volume": 13.47,
    "float_shares": 1848604,
    "float_millions": 1.85,
    "profile": "A"
  },
  {
    "symbol": "BTCT",
    "prev_close": 3.85,
    "pm_price": 5.3,
    "gap_pct": 37.66,
    "pm_volume": 3994187.0,
    "first_seen_et": "04:00",
    "sim_start": "04:00",
    "discovery_time": "04:00",
    "discovery_method": "ibkr_historical",
    "avg_daily_volume": 506053.0,
    "relative_volume": 7.89,
    "float_shares": 7175629,
    "float_millions": 7.18,
    "profile": "B"
  }
]