[
  {
    "symbol": "CAPS",
    "prev_close": 2.22,
    "pm_price": 2.97,
    "gap_pct": 33.78,
    "pm_volume": 1097.0,
    "first_seen_et": "05:10",
    "sim_start": "07:00",
    "float_shares": 5134148,
    "float_millions": 5.13,
    "profile": "B"
  },
  {
    "symbol": "HCAI",
    "prev_close": 8.13,
    "pm_price": 10.79,
    "gap_pct": 32.72,
    "pm_volume": 100.0,
    "first_seen_et": "07:00",
    "sim_start": "07:00",
    "float_shares": 4897515,
    "float_millions": 4.9,
    "profile": "A"
  },
  {
    "symbol": "MCRP",
    "prev_close": 3.6435,
    "pm_price": 4.7,
    "gap_pct": 29.0,
    "pm_volume": 300.0,
    "first_seen_et": "04:06",
    "sim_start": "07:00",
    "float_shares": 8787353,
    "float_millions": 8.79,
    "profile": "B"
  },
  {
    "symbol": "IPDN",
    "prev_close": 2.45,
    "pm_price": 3.07,
    "gap_pct": 25.31,
    "pm_volume": 44677.0,
    "first_seen_et": "04:03",
    "sim_start": "07:00",
    "float_shares": 2823630,
    "float_millions": 2.82,
    "profile": "A"
  },
  {
    "symbol": "SMCL",
    "prev_close": 15.22,
    "pm_price": 18.78,
    "gap_pct": 23.39,
    "pm_volume": 8521.0,
    "first_seen_et": "05:05",
    "sim_start": "07:00",
    "float_shares": null,
    "float_millions": null,
    "profile": "X"
  },
  {
    "symbol": "AIFF",
    "prev_close": 4.62,
    "pm_price": 5.6,
    "gap_pct": 21.21,
    "pm_volume": 85584.0,
    "first_seen_et": "04:03",
    "sim_start": "07:00",
    "float_shares": 6278345,
    "float_millions": 6.28,
    "profile": "B"
  },
  {
    "symbol": "SNOA",
    "prev_close": 3.25,
    "pm_price": 3.71,
    "gap_pct": 14.15,
    "pm_volume": 586.0,
    "first_seen_et": "05:43",
    "sim_start": "07:00",
    "float_shares": 1709673,
    "float_millions": 1.71,
    "profile": "A"
  },
  {
    "symbol": "DWTX",
    "prev_close": 5.67,
    "pm_price": 6.37,
    "gap_pct": 12.35,
    "pm_volume": 2099.0,
    "first_seen_et": "05:03",
    "sim_start": "07:00",
    "float_shares": 1354225,
    "float_millions": 1.35,
    "profile": "A"
  },
  {
    "symbol": "PLCE",
    "prev_close": 7.93,
    "pm_price": 8.84,
    "gap_pct": 11.48,
    "pm_volume": 250.0,
    "first_seen_et": "04:02",
    "sim_start": "07:00",
    "float_shares": 7730386,
    "float_millions": 7.73,
    "profile": "B"
  },
  {
    "symbol": "QNTM",
    "prev_close": 6.5,
    "pm_price": 7.18,
    "gap_pct": 10.46,
    "pm_volume": 32047.0,
    "first_seen_et": "04:00",
    "sim_start": "07:00",
    "float_shares": 3580945,
    "float_millions": 3.58,
    "profile": "A"
  },
  {
    "symbol": "CHAI",
    "prev_close": 2.08,
    "pm_price": 2.29,
    "gap_pct": 10.1,
    "pm_volume": 1213.0,
    "first_seen_et": "05:06",
    "sim_start": "07:00",
    "float_shares": 19,
    "float_millions": 0.0,
    "profile": "A"
  },
  {
    "symbol": "ROBN",
    "prev_close": 11.96,
    "pm_price": 13.16,
    "gap_pct": 10.03,
    "pm_volume": 13540.0,
    "first_seen_et": "04:00",
    "sim_start": "07:00",
    "float_shares": null,
    "float_millions": null,
    "profile": "X"
  }
]