[
  {
    "symbol": "TWG",
    "prev_close": 3.48,
    "pm_price": 7.75,
    "gap_pct": 122.7,
    "pm_volume": 9478348.0,
    "first_seen_et": "05:08",
    "sim_start": "07:00",
    "discovery_time": "07:00",
    "discovery_method": "precise",
    "avg_daily_volume": 93464.0,
    "relative_volume": 101.41,
    "precise_discovery": "06:50",
    "float_shares": 435581,
    "float_millions": 0.44,
    "profile": "A"
  },
  {
    "symbol": "BTTC",
    "prev_close": 1.7,
    "pm_price": 3.14,
    "gap_pct": 84.71,
    "pm_volume": 29798487.0,
    "first_seen_et": "04:00",
    "sim_start": "07:00",
    "discovery_time": "07:00",
    "discovery_method": "precise",
    "avg_daily_volume": 144577.0,
    "relative_volume": 206.11,
    "precise_discovery": "04:12",
    "float_shares": 1271887,
    "float_millions": 1.27,
    "profile": "A"
  },
  {
    "symbol": "IVF",
    "prev_close": 0.8124,
    "pm_price": 3.62,
    "gap_pct": 345.59,
    "pm_volume": 43686384.0,
    "first_seen_et": "04:00",
    "sim_start": "07:00",
    "discovery_time": "07:00",
    "discovery_method": "precise",
    "avg_daily_volume": 3211543.0,
    "relative_volume": 13.6,
    "precise_discovery": "04:00",
    "float_shares": 1725571,
    "float_millions": 1.73,
    "profile": "A"
  },
  {
    "symbol": "SDST",
    "prev_close": 3.78,
    "pm_price": 4.73,
    "gap_pct": 25.13,
    "pm_volume": 4709019.0,
    "first_seen_et": "07:45",
    "sim_start": "07:45",
    "discovery_time": "07:45",
    "discovery_method": "precise",
    "avg_daily_volume": 101977.0,
    "relative_volume": 46.18,
    "precise_discovery": "07:31",
    "float_shares": 6667372,
    "float_millions": 6.67,
    "profile": "B"
  },
  {
    "symbol": "ICON",
    "prev_close": 1.94,
    "pm_price": 2.86,
    "gap_pct": 47.42,
    "pm_volume": 12463348.0,
    "first_seen_et": "04:00",
    "sim_start": "07:00",
    "discovery_time": "07:00",
    "discovery_method": "precise",
    "avg_daily_volume": 993197.0,
    "relative_volume": 12.55,
    "precise_discovery": "04:01",
    "float_shares": 691645,
    "float_millions": 0.69,
    "profile": "A"
  },
  {
    "symbol": "POLA",
    "prev_close": 1.68,
    "pm_price": 2.12,
    "gap_pct": 26.19,
    "pm_volume": 4490129.0,
    "first_seen_et": "04:00",
    "sim_start": "07:00",
    "discovery_time": "07:00",
    "discovery_method": "precise",
    "avg_daily_volume": 255297.0,
    "relative_volume": 17.59,
    "precise_discovery": "04:03",
    "float_shares": 1848604,
    "float_millions": 1.85,
    "profile": "A"
  },
  {
    "symbol": "SHPH",
    "prev_close": 1.63,
    "pm_price": 2.79,
    "gap_pct": 71.17,
    "pm_volume": 3403217.0,
    "first_seen_et": "08:00",
    "sim_start": "08:00",
    "discovery_time": "08:00",
    "discovery_method": "precise",
    "avg_daily_volume": 783695.0,
    "relative_volume": 4.34,
    "precise_discovery": "07:57",
    "float_shares": 1600000,
    "float_millions": 1.6,
    "profile": "A"
  }
]