[
  {
    "symbol": "MSGY",
    "prev_close": 2.05,
    "pm_price": 6.18,
    "gap_pct": 201.46,
    "pm_volume": 80520.0,
    "first_seen_et": "04:00",
    "sim_start": "07:00",
    "float_shares": 3273250,
    "float_millions": 3.27,
    "profile": "A"
  },
  {
    "symbol": "MRNO",
    "prev_close": 1.8,
    "pm_price": 3.31,
    "gap_pct": 83.89,
    "pm_volume": 24078277.0,
    "first_seen_et": "04:00",
    "sim_start": "07:00",
    "float_shares": 1349131,
    "float_millions": 1.35,
    "profile": "A"
  },
  {
    "symbol": "KUST",
    "prev_close": 2.1,
    "pm_price": 2.68,
    "gap_pct": 27.62,
    "pm_volume": 4000884.0,
    "first_seen_et": "04:00",
    "sim_start": "07:00",
    "float_shares": 191919,
    "float_millions": 0.19,
    "profile": "A"
  },
  {
    "symbol": "NETG",
    "prev_close": 10.6633,
    "pm_price": 13.55,
    "gap_pct": 27.07,
    "pm_volume": 5667.0,
    "first_seen_et": "04:06",
    "sim_start": "07:00",
    "float_shares": null,
    "float_millions": null,
    "profile": "X"
  },
  {
    "symbol": "ENVB",
    "prev_close": 3.49,
    "pm_price": 4.37,
    "gap_pct": 25.21,
    "pm_volume": 2629.0,
    "first_seen_et": "04:05",
    "sim_start": "07:00",
    "float_shares": 500000,
    "float_millions": 0.5,
    "profile": "A"
  },
  {
    "symbol": "ATOM",
    "prev_close": 2.8,
    "pm_price": 3.42,
    "gap_pct": 22.14,
    "pm_volume": 9328.0,
    "first_seen_et": "04:00",
    "sim_start": "07:00",
    "float_shares": 35303656,
    "float_millions": 35.3,
    "profile": "B"
  },
  {
    "symbol": "NBY",
    "prev_close": 2.0,
    "pm_price": 2.39,
    "gap_pct": 19.5,
    "pm_volume": 14639.0,
    "first_seen_et": "04:01",
    "sim_start": "07:00",
    "float_shares": 25874719,
    "float_millions": 25.87,
    "profile": "B"
  },
  {
    "symbol": "FEAM",
    "prev_close": 2.26,
    "pm_price": 2.7,
    "gap_pct": 19.47,
    "pm_volume": 8532.0,
    "first_seen_et": "04:00",
    "sim_start": "07:00",
    "float_shares": 6171822,
    "float_millions": 6.17,
    "profile": "B"
  },
  {
    "symbol": "OKLS",
    "prev_close": 9.574,
    "pm_price": 11.4,
    "gap_pct": 19.07,
    "pm_volume": 37219.0,
    "first_seen_et": "04:00",
    "sim_start": "07:00",
    "float_shares": null,
    "float_millions": null,
    "profile": "X"
  },
  {
    "symbol": "NVNI",
    "prev_close": 1.7,
    "pm_price": 2.01,
    "gap_pct": 18.24,
    "pm_volume": 2485.0,
    "first_seen_et": "04:00",
    "sim_start": "07:00",
    "float_shares": 7028202,
    "float_millions": 7.03,
    "profile": "B"
  },
  {
    "symbol": "MENS",
    "prev_close": 2.53,
    "pm_price": 2.98,
    "gap_pct": 17.79,
    "pm_volume": 551.0,
    "first_seen_et": "05:29",
    "sim_start": "07:00",
    "float_shares": 28063591,
    "float_millions": 28.06,
    "profile": "B"
  },
  {
    "symbol": "ABVE",
    "prev_close": 2.21,
    "pm_price": 2.59,
    "gap_pct": 17.19,
    "pm_volume": 7661.0,
    "first_seen_et": "04:00",
    "sim_start": "07:00",
    "float_shares": 42806871,
    "float_millions": 42.81,
    "profile": "B"
  },
  {
    "symbol": "AZI",
    "prev_close": 2.5,
    "pm_price": 2.91,
    "gap_pct": 16.4,
    "pm_volume": 47357.0,
    "first_seen_et": "04:01",
    "sim_start": "07:00",
    "float_shares": 44450443,
    "float_millions": 44.45,
    "profile": "B"
  },
  {
    "symbol": "GRI",
    "prev_close": 4.11,
    "pm_price": 4.77,
    "gap_pct": 16.06,
    "pm_volume": 1337.0,
    "first_seen_et": "04:02",
    "sim_start": "07:00",
    "float_shares": 1445029,
    "float_millions": 1.45,
    "profile": "A"
  },
  {
    "symbol": "VMAR",
    "prev_close": 3.73,
    "pm_price": 4.3,
    "gap_pct": 15.28,
    "pm_volume": 404.0,
    "first_seen_et": "06:49",
    "sim_start": "07:00",
    "float_shares": 868696,
    "float_millions": 0.87,
    "profile": "A"
  },
  {
    "symbol": "SPHL",
    "prev_close": 4.77,
    "pm_price": 5.44,
    "gap_pct": 14.05,
    "pm_volume": 640.0,
    "first_seen_et": "04:43",
    "sim_start": "07:00",
    "float_shares": 474111,
    "float_millions": 0.47,
    "profile": "A"
  },
  {
    "symbol": "MSOX",
    "prev_close": 3.43,
    "pm_price": 3.9,
    "gap_pct": 13.7,
    "pm_volume": 4384.0,
    "first_seen_et": "07:00",
    "sim_start": "07:00",
    "float_shares": null,
    "float_millions": null,
    "profile": "X"
  },
  {
    "symbol": "LTRX",
    "prev_close": 7.16,
    "pm_price": 8.13,
    "gap_pct": 13.55,
    "pm_volume": 257876.0,
    "first_seen_et": "04:00",
    "sim_start": "07:00",
    "float_shares": 33387345,
    "float_millions": 33.39,
    "profile": "B"
  },
  {
    "symbol": "ARMU",
    "prev_close": 13.83,
    "pm_price": 15.66,
    "gap_pct": 13.23,
    "pm_volume": 500.0,
    "first_seen_et": "07:00",
    "sim_start": "07:00",
    "float_shares": null,
    "float_millions": null,
    "profile": "X"
  },
  {
    "symbol": "TNMG",
    "prev_close": 3.68,
    "pm_price": 4.16,
    "gap_pct": 13.04,
    "pm_volume": 991.0,
    "first_seen_et": "04:11",
    "sim_start": "07:00",
    "float_shares": 1150000,
    "float_millions": 1.15,
    "profile": "A"
  },
  {
    "symbol": "CJMB",
    "prev_close": 1.85,
    "pm_price": 2.09,
    "gap_pct": 12.97,
    "pm_volume": 2357.0,
    "first_seen_et": "04:00",
    "sim_start": "07:00",
    "float_shares": 1394675,
    "float_millions": 1.39,
    "profile": "A"
  },
  {
    "symbol": "AFRU",
    "prev_close": 10.9,
    "pm_price": 12.3,
    "gap_pct": 12.84,
    "pm_volume": 200.0,
    "first_seen_et": "07:12",
    "sim_start": "07:12",
    "float_shares": null,
    "float_millions": null,
    "profile": "X"
  },
  {
    "symbol": "CRWG",
    "prev_close": 5.61,
    "pm_price": 6.33,
    "gap_pct": 12.83,
    "pm_volume": 491643.0,
    "first_seen_et": "04:00",
    "sim_start": "07:00",
    "float_shares": 5196392,
    "float_millions": 5.2,
    "profile": "B"
  },
  {
    "symbol": "PLSM",
    "prev_close": 6.3,
    "pm_price": 7.1,
    "gap_pct": 12.7,
    "pm_volume": 120.0,
    "first_seen_et": "04:09",
    "sim_start": "07:00",
    "float_shares": 2061928,
    "float_millions": 2.06,
    "profile": "A"
  },
  {
    "symbol": "ARMG",
    "prev_close": 5.63,
    "pm_price": 6.34,
    "gap_pct": 12.61,
    "pm_volume": 13259.0,
    "first_seen_et": "04:56",
    "sim_start": "07:00",
    "float_shares": null,
    "float_millions": null,
    "profile": "X"
  },
  {
    "symbol": "MRAM",
    "prev_close": 13.11,
    "pm_price": 14.72,
    "gap_pct": 12.28,
    "pm_volume": 1576.0,
    "first_seen_et": "06:03",
    "sim_start": "07:00",
    "float_shares": 18536977,
    "float_millions": 18.54,
    "profile": "B"
  },
  {
    "symbol": "OM",
    "prev_close": 5.025,
    "pm_price": 5.64,
    "gap_pct": 12.24,
    "pm_volume": 748.0,
    "first_seen_et": "05:14",
    "sim_start": "07:00",
    "float_shares": 13062782,
    "float_millions": 13.06,
    "profile": "B"
  },
  {
    "symbol": "CRWU",
    "prev_close": 10.52,
    "pm_price": 11.8,
    "gap_pct": 12.17,
    "pm_volume": 33044.0,
    "first_seen_et": "04:00",
    "sim_start": "07:00",
    "float_shares": null,
    "float_millions": null,
    "profile": "X"
  },
  {
    "symbol": "MTVA",
    "prev_close": 2.34,
    "pm_price": 2.61,
    "gap_pct": 11.54,
    "pm_volume": 4305.0,
    "first_seen_et": "04:05",
    "sim_start": "07:00",
    "float_shares": 981536,
    "float_millions": 0.98,
    "profile": "A"
  },
  {
    "symbol": "SOPA",
    "prev_close": 2.02,
    "pm_price": 2.25,
    "gap_pct": 11.39,
    "pm_volume": 3138.0,
    "first_seen_et": "04:07",
    "sim_start": "07:00",
    "float_shares": 5698348,
    "float_millions": 5.7,
    "profile": "B"
  },
  {
    "symbol": "GWAV",
    "prev_close": 4.62,
    "pm_price": 5.13,
    "gap_pct": 11.04,
    "pm_volume": 340.0,
    "first_seen_et": "06:56",
    "sim_start": "07:00",
    "float_shares": 800000,
    "float_millions": 0.8,
    "profile": "A"
  },
  {
    "symbol": "AARD",
    "prev_close": 13.25,
    "pm_price": 14.7,
    "gap_pct": 10.94,
    "pm_volume": 349.0,
    "first_seen_et": "04:54",
    "sim_start": "07:00",
    "float_shares": 11173390,
    "float_millions": 11.17,
    "profile": "B"
  },
  {
    "symbol": "IDX",
    "prev_close": 15.04,
    "pm_price": 16.68,
    "gap_pct": 10.9,
    "pm_volume": 778.0,
    "first_seen_et": "04:00",
    "sim_start": "07:00",
    "float_shares": null,
    "float_millions": null,
    "profile": "X"
  },
  {
    "symbol": "GNLX",
    "prev_close": 2.76,
    "pm_price": 3.06,
    "gap_pct": 10.87,
    "pm_volume": 400.0,
    "first_seen_et": "07:00",
    "sim_start": "07:00",
    "float_shares": 30641346,
    "float_millions": 30.64,
    "profile": "B"
  },
  {
    "symbol": "PAVM",
    "prev_close": 8.12,
    "pm_price": 9.0,
    "gap_pct": 10.84,
    "pm_volume": 478.0,
    "first_seen_et": "07:05",
    "sim_start": "07:05",
    "float_shares": 700000,
    "float_millions": 0.7,
    "profile": "A"
  },
  {
    "symbol": "SMX",
    "prev_close": 14.81,
    "pm_price": 16.41,
    "gap_pct": 10.8,
    "pm_volume": 4904.0,
    "first_seen_et": "04:05",
    "sim_start": "07:00",
    "float_shares": 34663,
    "float_millions": 0.03,
    "profile": "A"
  },
  {
    "symbol": "MKDW",
    "prev_close": 3.07,
    "pm_price": 3.4,
    "gap_pct": 10.75,
    "pm_volume": 9766.0,
    "first_seen_et": "04:00",
    "sim_start": "07:00",
    "float_shares": 1167812,
    "float_millions": 1.17,
    "profile": "A"
  },
  {
    "symbol": "CGTL",
    "prev_close": 3.0,
    "pm_price": 3.32,
    "gap_pct": 10.67,
    "pm_volume": 1020.0,
    "first_seen_et": "07:11",
    "sim_start": "07:11",
    "float_shares": 1581065,
    "float_millions": 1.58,
    "profile": "A"
  },
  {
    "symbol": "ASTI",
    "prev_close": 5.68,
    "pm_price": 6.28,
    "gap_pct": 10.56,
    "pm_volume": 1989.0,
    "first_seen_et": "04:20",
    "sim_start": "07:00",
    "float_shares": 2963574,
    "float_millions": 2.96,
    "profile": "A"
  },
  {
    "symbol": "SBDS",
    "prev_close": 6.71,
    "pm_price": 7.39,
    "gap_pct": 10.13,
    "pm_volume": 390.0,
    "first_seen_et": "07:05",
    "sim_start": "07:05",
    "float_shares": 425535,
    "float_millions": 0.43,
    "profile": "A"
  },
  {
    "symbol": "DTCX",
    "prev_close": 2.3,
    "pm_price": 2.53,
    "gap_pct": 10.0,
    "pm_volume": 193.0,
    "first_seen_et": "07:00",
    "sim_start": "07:00",
    "float_shares": 11161022,
    "float_millions": 11.16,
    "profile": "B"
  }
]