[
  {
    "symbol": "CDIO",
    "prev_close": 2.79,
    "pm_price": 4.07,
    "gap_pct": 45.88,
    "pm_volume": 6536915.0,
    "first_seen_et": "06:25",
    "sim_start": "07:00",
    "float_shares": 1700473,
    "float_millions": 1.7,
    "profile": "A"
  },
  {
    "symbol": "OPEX",
    "prev_close": 14.92,
    "pm_price": 19.08,
    "gap_pct": 27.88,
    "pm_volume": 540.0,
    "first_seen_et": "06:03",
    "sim_start": "07:00",
    "float_shares": null,
    "float_millions": null,
    "profile": "X"
  },
  {
    "symbol": "FIEE",
    "prev_close": 3.19,
    "pm_price": 3.94,
    "gap_pct": 23.51,
    "pm_volume": 1231.0,
    "first_seen_et": "07:00",
    "sim_start": "07:00",
    "float_shares": 393061,
    "float_millions": 0.39,
    "profile": "A"
  },
  {
    "symbol": "BNAI",
    "prev_close": 3.76,
    "pm_price": 4.63,
    "gap_pct": 23.14,
    "pm_volume": 43428.0,
    "first_seen_et": "04:00",
    "sim_start": "07:00",
    "float_shares": 3300000,
    "float_millions": 3.3,
    "profile": "A"
  },
  {
    "symbol": "VSTL",
    "prev_close": 11.4,
    "pm_price": 13.7,
    "gap_pct": 20.18,
    "pm_volume": 2792.0,
    "first_seen_et": "04:21",
    "sim_start": "07:00",
    "float_shares": null,
    "float_millions": null,
    "profile": "X"
  },
  {
    "symbol": "ASTI",
    "prev_close": 3.95,
    "pm_price": 4.59,
    "gap_pct": 16.2,
    "pm_volume": 94001.0,
    "first_seen_et": "04:16",
    "sim_start": "07:00",
    "float_shares": 2963574,
    "float_millions": 2.96,
    "profile": "A"
  },
  {
    "symbol": "SOPA",
    "prev_close": 3.02,
    "pm_price": 3.49,
    "gap_pct": 15.56,
    "pm_volume": 45512.0,
    "first_seen_et": "04:00",
    "sim_start": "07:00",
    "float_shares": 5698348,
    "float_millions": 5.7,
    "profile": "B"
  },
  {
    "symbol": "GEMG",
    "prev_close": 5.13,
    "pm_price": 5.86,
    "gap_pct": 14.23,
    "pm_volume": 557.0,
    "first_seen_et": "07:00",
    "sim_start": "07:00",
    "float_shares": 55000,
    "float_millions": 0.06,
    "profile": "A"
  },
  {
    "symbol": "VNCE",
    "prev_close": 3.82,
    "pm_price": 4.35,
    "gap_pct": 13.87,
    "pm_volume": 3000.0,
    "first_seen_et": "07:00",
    "sim_start": "07:00",
    "float_shares": 2614089,
    "float_millions": 2.61,
    "profile": "A"
  },
  {
    "symbol": "LCDL",
    "prev_close": 3.4949,
    "pm_price": 3.95,
    "gap_pct": 13.02,
    "pm_volume": 1468.0,
    "first_seen_et": "05:09",
    "sim_start": "07:00",
    "float_shares": 270941,
    "float_millions": 0.27,
    "profile": "A"
  },
  {
    "symbol": "BENF",
    "prev_close": 5.15,
    "pm_price": 5.82,
    "gap_pct": 13.01,
    "pm_volume": 575.0,
    "first_seen_et": "04:49",
    "sim_start": "07:00",
    "float_shares": 1182156,
    "float_millions": 1.18,
    "profile": "A"
  },
  {
    "symbol": "ANGH",
    "prev_close": 4.03,
    "pm_price": 4.55,
    "gap_pct": 12.9,
    "pm_volume": 4095.0,
    "first_seen_et": "04:37",
    "sim_start": "07:00",
    "float_shares": 1714560,
    "float_millions": 1.71,
    "profile": "A"
  },
  {
    "symbol": "OPTX",
    "prev_close": 2.95,
    "pm_price": 3.32,
    "gap_pct": 12.54,
    "pm_volume": 9227.0,
    "first_seen_et": "04:07",
    "sim_start": "07:00",
    "float_shares": 5982184,
    "float_millions": 5.98,
    "profile": "B"
  },
  {
    "symbol": "BMNG",
    "prev_close": 3.84,
    "pm_price": 4.3,
    "gap_pct": 11.98,
    "pm_volume": 540577.0,
    "first_seen_et": "04:00",
    "sim_start": "07:00",
    "float_shares": 1975000,
    "float_millions": 1.98,
    "profile": "A"
  },
  {
    "symbol": "BMNU",
    "prev_close": 5.76,
    "pm_price": 6.42,
    "gap_pct": 11.46,
    "pm_volume": 2039014.0,
    "first_seen_et": "04:00",
    "sim_start": "07:00",
    "float_shares": null,
    "float_millions": null,
    "profile": "X"
  },
  {
    "symbol": "DWTX",
    "prev_close": 3.56,
    "pm_price": 3.96,
    "gap_pct": 11.24,
    "pm_volume": 7000.0,
    "first_seen_et": "05:37",
    "sim_start": "07:00",
    "float_shares": 1354225,
    "float_millions": 1.35,
    "profile": "A"
  },
  {
    "symbol": "SATG",
    "prev_close": 17.1372,
    "pm_price": 18.98,
    "gap_pct": 10.75,
    "pm_volume": 229.0,
    "first_seen_et": "04:05",
    "sim_start": "07:00",
    "float_shares": 393310,
    "float_millions": 0.39,
    "profile": "A"
  }
]