{
  "label": "I07_PARA_0.15",
  "last_date": "2026-04-02",
  "equity": 280990,
  "trades": [
    {
      "date": "2026-01-06",
      "symbol": "CYCN",
      "pnl": -187,
      "reason": "sq_vwap_exit",
      "window": "06:17-12:00"
    },
    {
      "date": "2026-01-12",
      "symbol": "BDSX",
      "pnl": -333,
      "reason": "sq_max_loss_hit",
      "window": "08:00-12:00"
    },
    {
      "date": "2026-01-12",
      "symbol": "BDSX",
      "pnl": -98,
      "reason": "sq_para_trail_exit",
      "window": "08:00-12:00"
    },
    {
      "date": "2026-01-12",
      "symbol": "BDSX",
      "pnl": -333,
      "reason": "sq_max_loss_hit",
      "window": "08:00-12:00"
    },
    {
      "date": "2026-01-12",
      "symbol": "OM",
      "pnl": 709,
      "reason": "sq_target_hit_exit_full",
      "window": "08:43-12:00"
    },
    {
      "date": "2026-01-12",
      "symbol": "OM",
      "pnl": -1231,
      "reason": "max_loss_hit",
      "window": "08:43-12:00"
    },
    {
      "date": "2026-01-13",
      "symbol": "AHMA",
      "pnl": 746,
      "reason": "sq_target_hit_exit_full",
      "window": "07:31-12:00"
    },
    {
      "date": "2026-01-13",
      "symbol": "AHMA",
      "pnl": 943,
      "reason": "sq_target_hit",
      "window": "07:31-12:00"
    },
    {
      "date": "2026-01-13",
      "symbol": "AHMA",
      "pnl": 8769,
      "reason": "bearish_engulfing_exit_full",
      "window": "07:31-12:00"
    },
    {
      "date": "2026-01-13",
      "symbol": "AHMA",
      "pnl": -967,
      "reason": "max_loss_hit",
      "window": "07:31-12:00"
    },
    {
      "date": "2026-01-13",
      "symbol": "AHMA",
      "pnl": 1829,
      "reason": "sq_target_hit_exit_full",
      "window": "07:31-12:00"
    },
    {
      "date": "2026-01-14",
      "symbol": "ROLR",
      "pnl": 3964,
      "reason": "sq_target_hit",
      "window": "08:23-12:00"
    },
    {
      "date": "2026-01-14",
      "symbol": "ROLR",
      "pnl": 22930,
      "reason": "epl_mp_time_exit(5bars)",
      "window": "08:23-12:00"
    },
    {
      "date": "2026-01-14",
      "symbol": "ROLR",
      "pnl": 10760,
      "reason": "sq_target_hit",
      "window": "08:23-12:00"
    },
    {
      "date": "2026-01-14",
      "symbol": "ROLR",
      "pnl": -1353,
      "reason": "bearish_engulfing_exit_full",
      "window": "08:23-12:00"
    },
    {
      "date": "2026-01-14",
      "symbol": "ROLR",
      "pnl": -1207,
      "reason": "bearish_engulfing_exit_full",
      "window": "08:23-12:00"
    },
    {
      "date": "2026-01-15",
      "symbol": "BNKK",
      "pnl": 197,
      "reason": "sq_para_trail_exit",
      "window": "08:04-12:00"
    },
    {
      "date": "2026-01-16",
      "symbol": "SVRE",
      "pnl": 346,
      "reason": "sq_para_trail_exit",
      "window": "06:49-12:00"
    },
    {
      "date": "2026-01-16",
      "symbol": "ACCL",
      "pnl": 2668,
      "reason": "sq_target_hit_exit_full",
      "window": "04:07-12:00"
    },
    {
      "date": "2026-01-16",
      "symbol": "ACCL",
      "pnl": 15642,
      "reason": "sq_target_hit",
      "window": "04:07-12:00"
    },
    {
      "date": "2026-01-23",
      "symbol": "BGL",
      "pnl": 2135,
      "reason": "sq_target_hit_exit_full",
      "window": "05:24-12:00"
    },
    {
      "date": "2026-01-26",
      "symbol": "BATL",
      "pnl": 1940,
      "reason": "sq_target_hit_exit_full",
      "window": "04:16-12:00"
    },
    {
      "date": "2026-01-26",
      "symbol": "BATL",
      "pnl": -2400,
      "reason": "max_loss_hit",
      "window": "04:16-12:00"
    },
    {
      "date": "2026-01-26",
      "symbol": "BATL",
      "pnl": -571,
      "reason": "epl_mp_time_exit(5bars)",
      "window": "04:16-12:00"
    },
    {
      "date": "2026-01-26",
      "symbol": "BATL",
      "pnl": 180,
      "reason": "bearish_engulfing_exit_full",
      "window": "04:16-12:00"
    },
    {
      "date": "2026-01-26",
      "symbol": "BATL",
      "pnl": -1085,
      "reason": "max_loss_hit",
      "window": "04:16-12:00"
    },
    {
      "date": "2026-02-02",
      "symbol": "FUSE",
      "pnl": 742,
      "reason": "sq_para_trail_exit",
      "window": "08:08-12:00"
    },
    {
      "date": "2026-02-03",
      "symbol": "NPT",
      "pnl": 74102,
      "reason": "sq_target_hit",
      "window": "07:42-12:00"
    },
    {
      "date": "2026-03-05",
      "symbol": "GXAI",
      "pnl": 3515,
      "reason": "sq_target_hit_exit_full",
      "window": "08:30-12:00"
    },
    {
      "date": "2026-03-05",
      "symbol": "GXAI",
      "pnl": -1577,
      "reason": "max_loss_hit",
      "window": "08:30-12:00"
    },
    {
      "date": "2026-03-05",
      "symbol": "GXAI",
      "pnl": 2074,
      "reason": "topping_wicky_exit_full",
      "window": "08:30-12:00"
    },
    {
      "date": "2026-03-05",
      "symbol": "GXAI",
      "pnl": -2036,
      "reason": "max_loss_hit",
      "window": "08:30-12:00"
    },
    {
      "date": "2026-03-05",
      "symbol": "GXAI",
      "pnl": -1364,
      "reason": "max_loss_hit",
      "window": "08:30-12:00"
    },
    {
      "date": "2026-03-18",
      "symbol": "ARTL",
      "pnl": 3177,
      "reason": "sq_target_hit_exit_full",
      "window": "07:42-12:00"
    },
    {
      "date": "2026-03-18",
      "symbol": "ARTL",
      "pnl": 3092,
      "reason": "bearish_engulfing_exit_full",
      "window": "07:42-12:00"
    },
    {
      "date": "2026-03-18",
      "symbol": "ARTL",
      "pnl": -1578,
      "reason": "max_loss_hit",
      "window": "07:42-12:00"
    },
    {
      "date": "2026-03-20",
      "symbol": "ANNA",
      "pnl": 3264,
      "reason": "sq_target_hit_exit_full",
      "window": "07:14-12:00"
    },
    {
      "date": "2026-03-20",
      "symbol": "ANNA",
      "pnl": -2479,
      "reason": "max_loss_hit",
      "window": "07:14-12:00"
    },
    {
      "date": "2026-03-20",
      "symbol": "ANNA",
      "pnl": -323,
      "reason": "bearish_engulfing_exit_full",
      "window": "07:14-12:00"
    },
    {
      "date": "2026-03-20",
      "symbol": "ANNA",
      "pnl": 1294,
      "reason": "bearish_engulfing_exit_full",
      "window": "07:14-12:00"
    },
    {
      "date": "2026-03-20",
      "symbol": "ANNA",
      "pnl": 376,
      "reason": "topping_wicky_exit_full",
      "window": "07:14-12:00"
    },
    {
      "date": "2026-03-23",
      "symbol": "AHMA",
      "pnl": 16843,
      "reason": "sq_target_hit",
      "window": "09:15-12:00"
    },
    {
      "date": "2026-03-23",
      "symbol": "AHMA",
      "pnl": 32768,
      "reason": "sq_target_hit_exit_full",
      "window": "09:15-12:00"
    },
    {
      "date": "2026-03-23",
      "symbol": "AHMA",
      "pnl": 46712,
      "reason": "sq_target_hit_exit_full",
      "window": "09:15-12:00"
    },
    {
      "date": "2026-03-23",
      "symbol": "AHMA",
      "pnl": 3365,
      "reason": "bearish_engulfing_exit_full",
      "window": "09:15-12:00"
    },
    {
      "date": "2026-03-23",
      "symbol": "AHMA",
      "pnl": -1073,
      "reason": "bearish_engulfing_exit_full",
      "window": "09:15-12:00"
    },
    {
      "date": "2026-03-24",
      "symbol": "ELAB",
      "pnl": 6103,
      "reason": "sq_target_hit",
      "window": "07:14-12:00"
    }
  ],
  "daily": [
    {
      "date": "2026-01-02",
      "trades": 0,
      "pnl": 0,
      "equity": 30000
    },
    {
      "date": "2026-01-03",
      "trades": 0,
      "pnl": 0,
      "equity": 30000
    },
    {
      "date": "2026-01-05",
      "trades": 0,
      "pnl": 0,
      "equity": 30000
    },
    {
      "date": "2026-01-06",
      "trades": 1,
      "pnl": -187,
      "equity": 29813,
      "symbols": "CYCN",
      "withdrawal": 0,
      "total_withdrawn": 0
    },
    {
      "date": "2026-01-07",
      "trades": 0,
      "pnl": 0,
      "equity": 29813
    },
    {
      "date": "2026-01-08",
      "trades": 0,
      "pnl": 0,
      "equity": 29813
    },
    {
      "date": "2026-01-09",
      "trades": 0,
      "pnl": 0,
      "equity": 29813
    },
    {
      "date": "2026-01-12",
      "trades": 5,
      "pnl": -1286,
      "equity": 28527,
      "symbols": "BDSX OM",
      "withdrawal": 0,
      "total_withdrawn": 0
    },
    {
      "date": "2026-01-13",
      "trades": 5,
      "pnl": 11320,
      "equity": 39847,
      "symbols": "AHMA",
      "withdrawal": 0,
      "total_withdrawn": 0
    },
    {
      "date": "2026-01-14",
      "trades": 5,
      "pnl": 35094,
      "equity": 74941,
      "symbols": "ROLR",
      "withdrawal": 0,
      "total_withdrawn": 0
    },
    {
      "date": "2026-01-15",
      "trades": 1,
      "pnl": 197,
      "equity": 75138,
      "symbols": "BNKK",
      "withdrawal": 0,
      "total_withdrawn": 0
    },
    {
      "date": "2026-01-16",
      "trades": 3,
      "pnl": 18656,
      "equity": 93794,
      "symbols": "SVRE ACCL",
      "withdrawal": 0,
      "total_withdrawn": 0
    },
    {
      "date": "2026-01-20",
      "trades": 0,
      "pnl": 0,
      "equity": 93794,
      "symbols": "",
      "withdrawal": 0,
      "total_withdrawn": 0
    },
    {
      "date": "2026-01-21",
      "trades": 0,
      "pnl": 0,
      "equity": 93794,
      "symbols": "",
      "withdrawal": 0,
      "total_withdrawn": 0
    },
    {
      "date": "2026-01-22",
      "trades": 0,
      "pnl": 0,
      "equity": 93794
    },
    {
      "date": "2026-01-23",
      "trades": 1,
      "pnl": 2135,
      "equity": 95929,
      "symbols": "BGL",
      "withdrawal": 0,
      "total_withdrawn": 0
    },
    {
      "date": "2026-01-26",
      "trades": 5,
      "pnl": -1936,
      "equity": 93993,
      "symbols": "BATL",
      "withdrawal": 0,
      "total_withdrawn": 0
    },
    {
      "date": "2026-01-27",
      "trades": 0,
      "pnl": 0,
      "equity": 93993,
      "symbols": "",
      "withdrawal": 0,
      "total_withdrawn": 0
    },
    {
      "date": "2026-01-28",
      "trades": 0,
      "pnl": 0,
      "equity": 93993
    },
    {
      "date": "2026-01-29",
      "trades": 0,
      "pnl": 0,
      "equity": 93993,
      "symbols": "",
      "withdrawal": 0,
      "total_withdrawn": 0
    },
    {
      "date": "2026-01-30",
      "trades": 0,
      "pnl": 0,
      "equity": 93993,
      "symbols": "",
      "withdrawal": 0,
      "total_withdrawn": 0
    },
    {
      "date": "2026-02-02",
      "trades": 1,
      "pnl": 742,
      "equity": 94735,
      "symbols": "FUSE",
      "withdrawal": 0,
      "total_withdrawn": 0
    },
    {
      "date": "2026-02-03",
      "trades": 1,
      "pnl": 74102,
      "equity": 168837,
      "symbols": "NPT",
      "withdrawal": 0,
      "total_withdrawn": 0
    },
    {
      "date": "2026-02-04",
      "trades": 0,
      "pnl": 0,
      "equity": 168837
    },
    {
      "date": "2026-02-05",
      "trades": 0,
      "pnl": 0,
      "equity": 168837
    },
    {
      "date": "2026-02-06",
      "trades": 0,
      "pnl": 0,
      "equity": 168837
    },
    {
      "date": "2026-02-09",
      "trades": 0,
      "pnl": 0,
      "equity": 168837,
      "symbols": "",
      "withdrawal": 0,
      "total_withdrawn": 0
    },
    {
      "date": "2026-02-10",
      "trades": 0,
      "pnl": 0,
      "equity": 168837
    },
    {
      "date": "2026-02-11",
      "trades": 0,
      "pnl": 0,
      "equity": 168837,
      "symbols": "",
      "withdrawal": 0,
      "total_withdrawn": 0
    },
    {
      "date": "2026-02-12",
      "trades": 0,
      "pnl": 0,
      "equity": 168837,
      "symbols": "",
      "withdrawal": 0,
      "total_withdrawn": 0
    },
    {
      "date": "2026-02-13",
      "trades": 0,
      "pnl": 0,
      "equity": 168837,
      "symbols": "",
      "withdrawal": 0,
      "total_withdrawn": 0
    },
    {
      "date": "2026-02-17",
      "trades": 0,
      "pnl": 0,
      "equity": 168837,
      "symbols": "",
      "withdrawal": 0,
      "total_withdrawn": 0
    },
    {
      "date": "2026-02-18",
      "trades": 0,
      "pnl": 0,
      "equity": 168837
    },
    {
      "date": "2026-02-19",
      "trades": 0,
      "pnl": 0,
      "equity": 168837
    },
    {
      "date": "2026-02-20",
      "trades": 0,
      "pnl": 0,
      "equity": 168837,
      "symbols": "",
      "withdrawal": 0,
      "total_withdrawn": 0
    },
    {
      "date": "2026-02-23",
      "trades": 0,
      "pnl": 0,
      "equity": 168837
    },
    {
      "date": "2026-02-24",
      "trades": 0,
      "pnl": 0,
      "equity": 168837,
      "symbols": "",
      "withdrawal": 0,
      "total_withdrawn": 0
    },
    {
      "date": "2026-02-25",
      "trades": 0,
      "pnl": 0,
      "equity": 168837
    },
    {
      "date": "2026-02-26",
      "trades": 0,
      "pnl": 0,
      "equity": 168837,
      "symbols": "",
      "withdrawal": 0,
      "total_withdrawn": 0
    },
    {
      "date": "2026-02-27",
      "trades": 0,
      "pnl": 0,
      "equity": 168837,
      "symbols": "",
      "withdrawal": 0,
      "total_withdrawn": 0
    },
    {
      "date": "2026-03-02",
      "trades": 0,
      "pnl": 0,
      "equity": 168837,
      "symbols": "",
      "withdrawal": 0,
      "total_withdrawn": 0
    },
    {
      "date": "2026-03-03",
      "trades": 0,
      "pnl": 0,
      "equity": 168837
    },
    {
      "date": "2026-03-04",
      "trades": 0,
      "pnl": 0,
      "equity": 168837
    },
    {
      "date": "2026-03-05",
      "trades": 5,
      "pnl": 612,
      "equity": 169449,
      "symbols": "GXAI",
      "withdrawal": 0,
      "total_withdrawn": 0
    },
    {
      "date": "2026-03-06",
      "trades": 0,
      "pnl": 0,
      "equity": 169449
    },
    {
      "date": "2026-03-09",
      "trades": 0,
      "pnl": 0,
      "equity": 169449,
      "symbols": "",
      "withdrawal": 0,
      "total_withdrawn": 0
    },
    {
      "date": "2026-03-10",
      "trades": 0,
      "pnl": 0,
      "equity": 169449
    },
    {
      "date": "2026-03-11",
      "trades": 0,
      "pnl": 0,
      "equity": 169449,
      "symbols": "",
      "withdrawal": 0,
      "total_withdrawn": 0
    },
    {
      "date": "2026-03-12",
      "trades": 0,
      "pnl": 0,
      "equity": 169449,
      "symbols": "",
      "withdrawal": 0,
      "total_withdrawn": 0
    },
    {
      "date": "2026-03-13",
      "trades": 0,
      "pnl": 0,
      "equity": 169449,
      "symbols": "",
      "withdrawal": 0,
      "total_withdrawn": 0
    },
    {
      "date": "2026-03-16",
      "trades": 0,
      "pnl": 0,
      "equity": 169449
    },
    {
      "date": "2026-03-17",
      "trades": 0,
      "pnl": 0,
      "equity": 169449
    },
    {
      "date": "2026-03-18",
      "trades": 3,
      "pnl": 4691,
      "equity": 174140,
      "symbols": "ARTL",
      "withdrawal": 0,
      "total_withdrawn": 0
    },
    {
      "date": "2026-03-19",
      "trades": 0,
      "pnl": 0,
      "equity": 174140,
      "symbols": "",
      "withdrawal": 0,
      "total_withdrawn": 0
    },
    {
      "date": "2026-03-20",
      "trades": 5,
      "pnl": 2132,
      "equity": 176272,
      "symbols": "ANNA",
      "withdrawal": 0,
      "total_withdrawn": 0
    },
    {
      "date": "2026-03-23",
      "trades": 5,
      "pnl": 98615,
      "equity": 274887,
      "symbols": "AHMA",
      "withdrawal": 0,
      "total_withdrawn": 0
    },
    {
      "date": "2026-03-24",
      "trades": 1,
      "pnl": 6103,
      "equity": 280990,
      "symbols": "ELAB",
      "withdrawal": 0,
      "total_withdrawn": 0
    },
    {
      "date": "2026-03-25",
      "trades": 0,
      "pnl": 0,
      "equity": 280990
    },
    {
      "date": "2026-03-26",
      "trades": 0,
      "pnl": 0,
      "equity": 280990
    },
    {
      "date": "2026-03-27",
      "trades": 0,
      "pnl": 0,
      "equity": 280990,
      "symbols": "",
      "withdrawal": 0,
      "total_withdrawn": 0
    },
    {
      "date": "2026-03-30",
      "trades": 0,
      "pnl": 0,
      "equity": 280990
    },
    {
      "date": "2026-03-31",
      "trades": 0,
      "pnl": 0,
      "equity": 280990
    },
    {
      "date": "2026-04-01",
      "trades": 0,
      "pnl": 0,
      "equity": 280990,
      "symbols": "",
      "withdrawal": 0,
      "total_withdrawn": 0
    },
    {
      "date": "2026-04-02",
      "trades": 0,
      "pnl": 0,
      "equity": 280990,
      "symbols": "",
      "withdrawal": 0,
      "total_withdrawn": 0
    }
  ]
}